hybrid_cloud_navigator/__init__.py
hybrid_cloud_navigator/main.py
hybrid_cloud_navigator/prompts.py
hybrid_cloud_navigator-2025.12.21174658.dist-info/METADATA
hybrid_cloud_navigator-2025.12.21174658.dist-info/WHEEL
hybrid_cloud_navigator-2025.12.21174658.dist-info/top_level.txt
hybrid_cloud_navigator-2025.12.21174658.dist-info/RECORD
