Metadata-Version: 2.4
Name: hybrid-cloud-navigator
Version: 2025.12.21174658
Summary: A new package that helps users understand and navigate the complexities of hybrid cloud environments in 2025. Users can input their specific hybrid cloud challenges, such as data gravity (the tendency
Author-email: hybrid-cloud-navigator <hi@eugene.plus>
License: MIT
Project-URL: Homepage, https://github.com/chigwell/hybrid-cloud-navigator
Requires-Python: >=3.9
Requires-Dist: langchain-llm7>=0.0.0
Requires-Dist: llmatch-messages>=0.0.0
Requires-Dist: langchain-core>=0.3.0
